extra_sensitive_variables.py
django_extra_sensitive_variables-1.0.2.dist-info/RECORD
django_extra_sensitive_variables-1.0.2.dist-info/METADATA
django_extra_sensitive_variables-1.0.2.dist-info/DESCRIPTION.rst
django_extra_sensitive_variables-1.0.2.dist-info/metadata.json
django_extra_sensitive_variables-1.0.2.dist-info/top_level.txt
django_extra_sensitive_variables-1.0.2.dist-info/WHEEL
