Metadata-Version: 2.0
Name: django-extra-sensitive-variables
Version: 1.0.2
Summary: Globally censor a set of default variable names in your Django error reports
Home-page: https://github.com/shaneallgeier/django-extra-sensitive-variables
Author: Shane Allgeier
Author-email: shaneallgeier@gmail.com
License: MIT
Platform: UNKNOWN
Classifier: Development Status :: 5 - Production/Stable
Classifier: Intended Audience :: Developers
Classifier: Natural Language :: English
Classifier: License :: OSI Approved :: MIT License
Classifier: Operating System :: OS Independent
Classifier: Programming Language :: Python
Classifier: Programming Language :: Python :: 2
Classifier: Programming Language :: Python :: 2.6
Classifier: Programming Language :: Python :: 2.7
Classifier: Programming Language :: Python :: 3
Classifier: Programming Language :: Python :: 3.3
Classifier: Topic :: Software Development :: Libraries :: Python Modules
Classifier: Framework :: Django
